[
  {
    "id": 1,
    "title": "Vamos brincar de completar palavras!",
    "description": "Veja a figura do animal e tente descobrir qual sílaba está faltando para completar o nome dele. É como um quebra-cabeça de palavras!",
    "slug": "complete-com-os-animais"
  },
  {
    "id": 2,
    "title": "Forme a palavra",
    "description": "Lorem ipsum dolor sit amet consectetur adipisicing elit In odit"
  },
  {
    "id": 3,
    "title": "Identique a imagem",
    "description": "Lorem ipsum dolor sit amet consectetur adipisicing elit In odit"
  },
  {
    "id": 4,
    "title": "Desafio de Matemática",
    "description": "Lorem ipsum dolor sit amet consectetur adipisicing elit In odit"
  },
  {
    "id": 5,
    "title": "Contar dedinhos",
    "description": "Lorem ipsum dolor sit amet consectetur adipisicing elit In odit"
  }
]